trns/__init__.py
trns/bot/__init__.py
trns/bot/output_handler.py
trns/bot/routes.py
trns/bot/server.py
trns/bot/utils.py
trns/cli/main.py
trns/transcription/__init__.py
trns/transcription/language_model.py
trns/transcription/main.py
trns/transcription/pipeline.py
trns/transcription/subtitle_extractor.py
trns/transcription/whisper_transcriber.py
trns-0.1.1.dist-info/licenses/LICENSE
trns-0.1.1.dist-info/METADATA
trns-0.1.1.dist-info/WHEEL
trns-0.1.1.dist-info/entry_points.txt
trns-0.1.1.dist-info/top_level.txt
trns-0.1.1.dist-info/RECORD
