Metadata-Version: 2.4
Name: trns
Version: 0.1.1
Summary: Transcription and summarization tool for YouTube, Twitter/X.com videos, and local files with automatic translation and language model processing
Author-email: "Misha S." <862andfurther@gmai.com>
License-Expression: MIT
Project-URL: Homepage, https://github.com/kakoyvostorg/trns
Project-URL: Documentation, https://github.com/kakoyvostorg/trns/tree/main/docs
Project-URL: Repository, https://github.com/kakoyvostorg/trns
Project-URL: Issues, https://github.com/kakoyvostorg/trns/issues
Keywords: transcription,whisper,youtube,telegram,translation,language-model
Classifier: Development Status :: 4 - Beta
Classifier: Intended Audience :: Developers
Classifier: Programming Language :: Python :: 3
Classifier: Programming Language :: Python :: 3.8
Classifier: Programming Language :: Python :: 3.9
Classifier: Programming Language :: Python :: 3.10
Classifier: Programming Language :: Python :: 3.11
Classifier: Programming Language :: Python :: 3.12
Classifier: Programming Language :: Python :: 3.13
Classifier: Topic :: Multimedia :: Sound/Audio :: Speech
Classifier: Topic :: Software Development :: Libraries :: Python Modules
Requires-Python: >=3.8
License-File: LICENSE
Requires-Dist: youtube-transcript-api>=0.6.0
Requires-Dist: yt-dlp>=2023.10.7
Requires-Dist: faster-whisper>=0.9.0
Requires-Dist: deep-translator>=1.11.4
Requires-Dist: openai>=1.0.0
Requires-Dist: tqdm>=4.66.0
Requires-Dist: python-telegram-bot>=20.0
Requires-Dist: fastapi>=0.104.0
Requires-Dist: uvicorn[standard]>=0.24.0
Requires-Dist: python-dotenv>=1.0.0
Requires-Dist: pydantic>=2.0.0
Provides-Extra: dev
Requires-Dist: pytest>=7.0.0; extra == "dev"
Requires-Dist: ruff>=0.1.0; extra == "dev"
Requires-Dist: mypy>=1.0.0; extra == "dev"
Dynamic: license-file
